<?xml version="1.0" encoding="UTF-8"?>
<objects serializationModel="Studio.01.09.00">
    <object class="EncodingSetting" id="{0aaa0a08-0a87-4d0e-bd1c-3ab467370348}">
        <property name="encodingFormat">
            <value>3</value>
        </property>
        <property name="quality">
            <value>37</value>
        </property>
        <relationship name="platform">
            <destination>{19d2853e-e924-4fd2-8df5-96e096e22d32}</destination>
        </relationship>
        <relationship name="encodable">
            <destination>{19d2853e-e924-4fd2-8df5-96e096e22d32}</destination>
        </relationship>
    </object>
</objects>
