<?xml version="1.0" encoding="UTF-8"?>
<objects serializationModel="Studio.01.10.00">
    <object class="Event" id="{c85adbf4-2d80-45c9-b915-e4f450182e36}">
        <property name="name">
            <value>Enviro - Mech Door</value>
        </property>
        <property name="outputFormat">
            <value>2</value>
        </property>
        <relationship name="folder">
            <destination>{320f4f92-7e1e-414c-bd1c-a6ec48ef0757}</destination>
        </relationship>
        <relationship name="mixer">
            <destination>{1f7198a6-0c56-46ca-977d-66a460a90469}</destination>
        </relationship>
        <relationship name="masterTrack">
            <destination>{cf0840bb-a53c-4591-8e90-7db7a7a0e430}</destination>
        </relationship>
        <relationship name="mixerInput">
            <destination>{aa39d9f4-71bf-407d-9114-f1be82e59fac}</destination>
        </relationship>
        <relationship name="automatableProperties">
            <destination>{7cb7e5f7-9b05-44da-8eef-854894cbeaba}</destination>
        </relationship>
        <relationship name="markerTracks">
            <destination>{b172ed16-7c65-4e1e-bdcd-6ec555d9677c}</destination>
        </relationship>
        <relationship name="groupTracks">
            <destination>{1fed10a7-5064-481f-9ad6-6dc2b5b40686}</destination>
        </relationship>
        <relationship name="timeline">
            <destination>{787c90d7-8701-4f6b-a1e7-8598b8cb6c21}</destination>
        </relationship>
    </object>
    <object class="EventMixer" id="{1f7198a6-0c56-46ca-977d-66a460a90469}">
        <relationship name="masterBus">
            <destination>{be0978ec-a8c9-403b-8d04-0ebc836b87a4}</destination>
        </relationship>
    </object>
    <object class="MasterTrack" id="{cf0840bb-a53c-4591-8e90-7db7a7a0e430}">
        <relationship name="mixerGroup">
            <destination>{be0978ec-a8c9-403b-8d04-0ebc836b87a4}</destination>
        </relationship>
    </object>
    <object class="MixerInput" id="{aa39d9f4-71bf-407d-9114-f1be82e59fac}">
        <relationship name="effectChain">
            <destination>{c2f06a83-917c-4e86-acf3-085f4e204a29}</destination>
        </relationship>
        <relationship name="panner">
            <destination>{00e1b12d-6a75-4b3d-a4f3-83b33fb3a61d}</destination>
        </relationship>
        <relationship name="output">
            <destination>{733ff64d-4620-4e9b-83d7-a5285b629063}</destination>
        </relationship>
    </object>
    <object class="EventAutomatableProperties" id="{7cb7e5f7-9b05-44da-8eef-854894cbeaba}"/>
    <object class="MarkerTrack" id="{b172ed16-7c65-4e1e-bdcd-6ec555d9677c}"/>
    <object class="GroupTrack" id="{1fed10a7-5064-481f-9ad6-6dc2b5b40686}">
        <relationship name="mixerGroup">
            <destination>{19e680a9-d5ba-4de7-89ee-cc47d71b5904}</destination>
        </relationship>
    </object>
    <object class="Timeline" id="{787c90d7-8701-4f6b-a1e7-8598b8cb6c21}"/>
    <object class="EventMixerMaster" id="{be0978ec-a8c9-403b-8d04-0ebc836b87a4}">
        <relationship name="effectChain">
            <destination>{2b24fe8f-086d-425d-9c06-20d0f83b6ecf}</destination>
        </relationship>
        <relationship name="panner">
            <destination>{3f6ae4b3-37a6-430c-8d20-ce3efc0832bd}</destination>
        </relationship>
        <relationship name="mixer">
            <destination>{1f7198a6-0c56-46ca-977d-66a460a90469}</destination>
        </relationship>
    </object>
    <object class="MixerBusEffectChain" id="{c2f06a83-917c-4e86-acf3-085f4e204a29}">
        <relationship name="effects">
            <destination>{7df95d31-d081-482a-bca4-6329b5404284}</destination>
        </relationship>
    </object>
    <object class="MixerBusPanner" id="{00e1b12d-6a75-4b3d-a4f3-83b33fb3a61d}"/>
    <object class="EventMixerGroup" id="{19e680a9-d5ba-4de7-89ee-cc47d71b5904}">
        <property name="name">
            <value>Audio 1</value>
        </property>
        <relationship name="effectChain">
            <destination>{5428a3b8-eceb-4dbb-9d4c-b1163e30a261}</destination>
        </relationship>
        <relationship name="panner">
            <destination>{b6c5dc2e-71ce-43d8-b42f-bb81565d2571}</destination>
        </relationship>
        <relationship name="output">
            <destination>{be0978ec-a8c9-403b-8d04-0ebc836b87a4}</destination>
        </relationship>
    </object>
    <object class="MixerBusEffectChain" id="{2b24fe8f-086d-425d-9c06-20d0f83b6ecf}">
        <relationship name="effects">
            <destination>{2f128f28-c1cd-4cef-bba5-aba6031ffe22}</destination>
            <destination>{e9017744-b239-447d-9515-740f26ae9f31}</destination>
        </relationship>
    </object>
    <object class="MixerBusPanner" id="{3f6ae4b3-37a6-430c-8d20-ce3efc0832bd}"/>
    <object class="MixerBusFader" id="{7df95d31-d081-482a-bca4-6329b5404284}"/>
    <object class="MixerBusEffectChain" id="{5428a3b8-eceb-4dbb-9d4c-b1163e30a261}">
        <relationship name="effects">
            <destination>{0c68b389-d8ea-4972-933d-e81d94d8c67a}</destination>
        </relationship>
    </object>
    <object class="MixerBusPanner" id="{b6c5dc2e-71ce-43d8-b42f-bb81565d2571}"/>
    <object class="MixerBusFader" id="{2f128f28-c1cd-4cef-bba5-aba6031ffe22}"/>
    <object class="ProxyEffect" id="{e9017744-b239-447d-9515-740f26ae9f31}">
        <property name="inputFormat">
            <value>0</value>
        </property>
        <relationship name="preset">
            <destination>{33e07fc8-31d1-0d11-3247-774b613aa22e}</destination>
        </relationship>
    </object>
    <object class="MixerBusFader" id="{0c68b389-d8ea-4972-933d-e81d94d8c67a}"/>
</objects>
